ecowater_softener/__init__.py
ecowater_softener/const.py
ecowater_softener/ecowater.py
ecowater_softener-2.1.3.dist-info/LICENSE
ecowater_softener-2.1.3.dist-info/METADATA
ecowater_softener-2.1.3.dist-info/WHEEL
ecowater_softener-2.1.3.dist-info/top_level.txt
ecowater_softener-2.1.3.dist-info/RECORD
