Metadata-Version: 2.1
Name: ecowater-softener
Version: 2.1.3
Summary: A small package to pull data from Ecowater water softeners
Home-page: https://github.com/barleybobs/ecowater-softener
Author: barleybobs
Classifier: Programming Language :: Python :: 3
Classifier: License :: OSI Approved :: MIT License
Classifier: Operating System :: OS Independent
License-File: LICENSE
Requires-Dist: ayla-iot-unofficial==1.4.1
